Metadata-Version: 2.1
Name: project-makefile
Version: 0.0.6
Summary: A generic makefile for projects.
Home-page: https://github.com/project-makefile/project-makefile
Author: Alex Clark
Author-email: aclark@aclark.net
License: UNKNOWN
Platform: UNKNOWN
License-File: LICENSE.rst
